[
    {
        "userID": "5e2fbf77-8406-4ef7-a567-36daeb808430",
        "firstNames": "Greg",
        "lastName": "Heffley",
        "username": "greg9920",
        "password": "javaIsCool!",
        "email": "greg9920@heffley.com",
        "phoneNumber": "9999999999",
        "department": "Surrey County Police",
        "badgeID": "9909328928409289",
        "caseCount": 2,
        "editAccess": false
    },{
        "userID": "049d1490-5919-4652-b901-040086e41687",
        "firstNames": "Manny",
        "lastName": "Heffley",
        "username": "manny128499",
        "password": "mannyAwesome449",
        "email": "manny128499@heffley.com",
        "phoneNumber": "2799831988",
        "department": "Elementary County Police",
        "badgeID": "976577811223378",
        "caseCount": 1,
        "editAccess": false
    },{
        "userID": "48d384bf-f11f-4062-99df-11583454571e",
        "firstNames": "Rodrick",
        "lastName": "Heffley",
        "username": "LoadedDiperFan",
        "password": "DiperRockin99",
        "email": "LoadedDiper@heffley.com",
        "phoneNumber": "4637823485",
        "department": "Mettal County Police",
        "badgeID": "8971937811992278",
        "caseCount": 1,
        "editAccess": false
    },{
        "userID": "5fd7100c-4e3b-4721-a460-bc777ababaa3",
        "firstNames": "Rowley",
        "lastName": "Jefferson",
        "username": "ZooWeeMama",
        "password": "TheCheeseTouch2007",
        "email": "ZooWeeMama@jefferson.com",
        "phoneNumber": "3479862305",
        "department": "Annoi County Police",
        "badgeID": "2761623409898928",
        "caseCount": 2,
        "editAccess": false
    }
]